aio/tasks/__init__.py
aio/tasks/exceptions.py
aio/tasks/py.typed
aio/tasks/tasks.py
aio.tasks-0.0.5.dist-info/METADATA
aio.tasks-0.0.5.dist-info/WHEEL
aio.tasks-0.0.5.dist-info/namespace_packages.txt
aio.tasks-0.0.5.dist-info/top_level.txt
aio.tasks-0.0.5.dist-info/RECORD
