Metadata-Version: 2.1
Name: aio.tasks
Version: 0.0.5
Summary: A collection of task utils for asyncio
Home-page: https://github.com/envoyproxy/pytooling/tree/main/aio.tasks
Author: Ryan Northey
Author-email: ryan@synca.io
Maintainer: Ryan Northey
Maintainer-email: ryan@synca.io
License: Apache Software License 2.0
Platform: UNKNOWN
Requires-Dist: aio.functional (>=0.0.10)
